Text2JSON/__init__.py
Text2JSON/entity_named_recog/__init__.py
Text2JSON/entity_named_recog/day_entity_recognition.py
Text2JSON/entity_named_recog/entity_recognition.py
Text2JSON/entity_named_recog/entity_utils.py
Text2JSON/entity_named_recog/hour_entity_recognition.py
Text2JSON/entity_named_recog/minute_entity_recognition.py
Text2JSON/entity_named_recog/month_entity_recognition.py
Text2JSON/entity_named_recog/proper_noun_recognition.py
Text2JSON/entity_named_recog/quarter_entity_recognition.py
Text2JSON/entity_named_recog/year_entity_recognition.py
Text2JSON/evaluator/__init__.py
Text2JSON/evaluator/column_evaluator.py
Text2JSON/evaluator/schema_evaluator.py
Text2JSON/featurizer/Input_SQL.py
Text2JSON/featurizer/__init__.py
Text2JSON/featurizer/column_featurizer.py
Text2JSON/featurizer/schema_featurizer.py
Text2JSON/featurizer/schema_parser.py
Text2JSON/model/__init__.py
Text2JSON/model/base_model.py
Text2JSON/model/column_model.py
Text2JSON/model/schema_model.py
Text2JSON/predict/__init__.py
Text2JSON/predict/prediction.py
Text2JSON/preprocess_data/__init__.py
Text2JSON/preprocess_data/extract_schema.py
Text2JSON/preprocess_data/process_raw_data.py
Text2JSON/preprocess_data/process_raw_schema.py
Text2JSON/train/__init__.py
Text2JSON/train/data_utils.py
Text2JSON/train/evaluator.py
Text2JSON/train/train_model.py
Text2JSON/train/utils.py
Text2JSON-0.1.9.dist-info/LICENSE
Text2JSON-0.1.9.dist-info/METADATA
Text2JSON-0.1.9.dist-info/WHEEL
Text2JSON-0.1.9.dist-info/top_level.txt
Text2JSON-0.1.9.dist-info/RECORD
